gcal_cmd_tool/__init__.py
gcal_cmd_tool/libs/__init__.py
gcal_cmd_tool/libs/acl.py
gcal_cmd_tool/libs/calendars.py
gcal_cmd_tool/main.py
gcal_cmd_tool-0.1.1.dist-info/entry_points.txt
gcal_cmd_tool-0.1.1.dist-info/LICENSE
gcal_cmd_tool-0.1.1.dist-info/WHEEL
gcal_cmd_tool-0.1.1.dist-info/METADATA
gcal_cmd_tool-0.1.1.dist-info/RECORD
