Metadata-Version: 2.1
Name: gcal-cmd-tool
Version: 0.1.1
Summary: A command line tool to manage Google Calendars
Author: Alexandre Santos
Author-email: ajvsms@gmail.com
Requires-Python: >=3.9,<4.0
Classifier: Programming Language :: Python :: 3
Classifier: Programming Language :: Python :: 3.10
Classifier: Programming Language :: Python :: 3.9
Requires-Dist: google-api-python-client (>=2.42.0,<3.0.0)
Requires-Dist: google-auth-httplib2 (>=0.1.0,<0.2.0)
Requires-Dist: google-auth-oauthlib (>=0.5.1,<0.6.0)
Requires-Dist: typer[all] (>=0.4.1,<0.5.0)
